LICENSE
MANIFEST.in
NOTICES.rst
ecs_composex/.gitignore
ecs_composex/__init__.py
ecs_composex/acm/__init__.py
ecs_composex/acm/acm_module.py
ecs_composex/acm/acm_params.py
ecs_composex/acm/acm_stack.py
ecs_composex/acm/acm_stack_helpers.py
ecs_composex/acm/x-acm.spec.json
ecs_composex/alarms/__init__.py
ecs_composex/alarms/alarms_ecs.py
ecs_composex/alarms/alarms_elbv2.py
ecs_composex/alarms/alarms_helpers.py
ecs_composex/alarms/alarms_module.py
ecs_composex/alarms/alarms_params.py
ecs_composex/alarms/alarms_stack.py
ecs_composex/alarms/x-alarms.spec.json
ecs_composex/aps/__init__.py
ecs_composex/aps/aps_module.py
ecs_composex/aps/aps_parameters.py
ecs_composex/aps/aps_perms.json
ecs_composex/aps/aps_stack.py
ecs_composex/aps/x-aps.spec.json
ecs_composex/cli.py
ecs_composex/cloudmap/__init__.py
ecs_composex/cloudmap/cloudmap_ecs.py
ecs_composex/cloudmap/cloudmap_helpers.py
ecs_composex/cloudmap/cloudmap_module.py
ecs_composex/cloudmap/cloudmap_params.py
ecs_composex/cloudmap/cloudmap_stack.py
ecs_composex/cloudmap/cloudmap_x_resources.py
ecs_composex/cloudmap/x-cloudmap.spec.json
ecs_composex/codeguru_profiler/__init__.py
ecs_composex/codeguru_profiler/codeguru_profiler_aws.py
ecs_composex/codeguru_profiler/codeguru_profiler_module.py
ecs_composex/codeguru_profiler/codeguru_profiler_params.py
ecs_composex/codeguru_profiler/codeguru_profiler_perms.json
ecs_composex/codeguru_profiler/codeguru_profiler_stack.py
ecs_composex/cognito_userpool/__init__.py
ecs_composex/cognito_userpool/cognito_params.py
ecs_composex/cognito_userpool/cognito_userpool_module.py
ecs_composex/cognito_userpool/cognito_userpool_stack.py
ecs_composex/cognito_userpool/x-cognito_userpool.spec.json
ecs_composex/common/__init__.py
ecs_composex/common/aws.py
ecs_composex/common/cfn_conditions.py
ecs_composex/common/cfn_params.py
ecs_composex/common/ecs_composex.py
ecs_composex/common/envsubst.py
ecs_composex/common/files.py
ecs_composex/common/logging.py
ecs_composex/common/settings.py
ecs_composex-1.1.8.dist-info/LICENSE
ecs_composex-1.1.8.dist-info/METADATA
ecs_composex-1.1.8.dist-info/NOTICES.rst
ecs_composex-1.1.8.dist-info/WHEEL
ecs_composex-1.1.8.dist-info/entry_points.txt
ecs_composex-1.1.8.dist-info/RECORD
