Metadata-Version: 2.1
Name: ecs_composex
Version: 1.1.8
Summary: Manage, Configure and Deploy your services and AWS services and applications from your docker-compose definition
License: MPL-2.0
Keywords: compose-x,aws,cloudformation,docker,compose
Author: John Preston
Author-email: john@compose-x.io
Maintainer: John Preston
Maintainer-email: john@compose-x.io
Requires-Python: >=3.9,<4.0
Classifier: Development Status :: 5 - Production/Stable
Classifier: Intended Audience :: Developers
Classifier: Intended Audience :: Information Technology
Classifier: Intended Audience :: System Administrators
Classifier: License :: OSI Approved
Classifier: License :: OSI Approved :: Mozilla Public License 2.0 (MPL 2.0)
Classifier: Natural Language :: English
Classifier: Programming Language :: Python :: 3
Classifier: Programming Language :: Python :: 3.9
Classifier: Programming Language :: Python :: 3.10
Classifier: Programming Language :: Python :: 3.11
Classifier: Programming Language :: Python :: 3.12
Classifier: Programming Language :: Python :: 3.13
Classifier: Programming Language :: Python :: 3.8
Provides-Extra: ecrscan
Requires-Dist: Jinja2 (>=3.1.2,<4.0.0)
Requires-Dist: PyYAML (>=6.0,<7.0)
Requires-Dist: boto3 (>=1.26,<2.0)
Requires-Dist: compose-x-common (>=1.4,<2.0)
Requires-Dist: compose-x-render (>=1.1,<2.0)
Requires-Dist: docker (>=6.0.1,<8.0)
Requires-Dist: ecr-scan-reporter (>=0.4.8,<0.5.0) ; extra == "ecrscan"
Requires-Dist: importlib-resources (>=6.4,<7.0)
Requires-Dist: jsonschema (>=4.21)
Requires-Dist: requests (>=2.28,<3.0)
Requires-Dist: retry2 (>=0.9,<0.10)
Requires-Dist: tabulate (>=0.8,<0.9)
Requires-Dist: troposphere (>=4.5.3,<5.0)
Requires-Dist: troposphere-awscommunity-applicationautoscaling-scheduledaction (>=0.1.1,<0.2.0)
Project-URL: Bug Tracker, https://github.com/compose-x/ecs_composex/issues
Project-URL: Blog, https://blog.compose-x.io/
Project-URL: Documentation, https://docs.compose-x.io/
Project-URL: Labs, https://labs.compose-x.io/
